pprint_tools/__init__.py
pprint_tools/app.py
pprint_tools-0.0.3.dist-info/METADATA
pprint_tools-0.0.3.dist-info/WHEEL
pprint_tools-0.0.3.dist-info/RECORD
